makereadme/__init__.py
makereadme/cli.py
makereadme-0.0.2.dist-info/licenses/LICENSE
makereadme-0.0.2.dist-info/licenses/LICENSE-PT
makereadme-0.0.2.dist-info/METADATA
makereadme-0.0.2.dist-info/WHEEL
makereadme-0.0.2.dist-info/entry_points.txt
makereadme-0.0.2.dist-info/top_level.txt
makereadme-0.0.2.dist-info/RECORD
