Metadata-Version: 2.4
Name: makereadme
Version: 0.0.2
Summary: A simple CLI tool to generate README.md files from Python scripts
Author: Glayton Ricardo
License: MIT License
Project-URL: Homepage, https://github.com/GR-MARTINS/mkreadme
Requires-Python: >=3.8
License-File: LICENSE
License-File: LICENSE-PT
Dynamic: license-file
